scalifiai/__init__.py
scalifiai/base.py
scalifiai/constants.py
scalifiai/credentials.py
scalifiai/exceptions.py
scalifiai/request_manager.py
scalifiai/mcs/__init__.py
scalifiai/mcs/constants.py
scalifiai/mcs/exceptions.py
scalifiai/mcs/main.py
scalifiai/mcs/frameworks/__init__.py
scalifiai/mcs/frameworks/base.py
scalifiai/mcs/frameworks/constants.py
scalifiai/mcs/frameworks/exceptions.py
scalifiai/mcs/frameworks/schema.py
scalifiai/mcs/frameworks/utils.py
scalifiai/mcs/frameworks/keras/__init__.py
scalifiai/mcs/frameworks/keras/constants.py
scalifiai/mcs/frameworks/keras/exceptions.py
scalifiai/mcs/frameworks/keras/main.py
scalifiai/mcs/frameworks/pytorch/__init__.py
scalifiai/mcs/frameworks/pytorch/constants.py
scalifiai/mcs/frameworks/pytorch/exceptions.py
scalifiai/mcs/frameworks/pytorch/main.py
scalifiai/mcs/metadata/__init__.py
scalifiai/mcs/metadata/constants.py
scalifiai/mcs/metadata/exceptions.py
scalifiai/mcs/metadata/main.py
scalifiai/mcs/metadata/schemas.py
scalifiai/mcs/model/__init__.py
scalifiai/mcs/model/constants.py
scalifiai/mcs/model/exceptions.py
scalifiai/mcs/model/main.py
scalifiai/mcs/model/schemas.py
scalifiai/mcs/model_version/__init__.py
scalifiai/mcs/model_version/constants.py
scalifiai/mcs/model_version/exceptions.py
scalifiai/mcs/model_version/main.py
scalifiai/mcs/model_version/schemas.py
scalifiai_client-1.3.0a8.dist-info/LICENSE
scalifiai_client-1.3.0a8.dist-info/METADATA
scalifiai_client-1.3.0a8.dist-info/WHEEL
scalifiai_client-1.3.0a8.dist-info/top_level.txt
scalifiai_client-1.3.0a8.dist-info/RECORD
