Metadata-Version: 2.1
Name: scalifiai-client
Version: 1.3.0a8
Summary: SCALIFI AI NO CODE PLATFORM
Author-email: Scalifi Ai <helpdesk@scalifiai.com>
Project-URL: Homepage, https://github.com/Ai-Bloc-24
Keywords: ai,ml,artificial intelligence,machine learning,no-code,no code,low-code,low code,big-data,big data
Classifier: License :: OSI Approved :: MIT License
Classifier: Programming Language :: Python
Classifier: Programming Language :: Python :: 3
Requires-Python: >=3.7
License-File: LICENSE
Requires-Dist: pydantic >=2.0
Requires-Dist: pandas >=1.3.0
Requires-Dist: humanize >=2.0.0
Requires-Dist: tzlocal >=2.1
Requires-Dist: requests >=2.0.0
Provides-Extra: tf
Requires-Dist: tensorflow <=2.15.1,>=2.2.0 ; extra == 'tf'
Requires-Dist: pydantic >=2.0 ; extra == 'tf'
Requires-Dist: pandas >=1.3.0 ; extra == 'tf'
Requires-Dist: humanize >=2.0.0 ; extra == 'tf'
Requires-Dist: tzlocal >=2.1 ; extra == 'tf'
Requires-Dist: requests >=2.0.0 ; extra == 'tf'
Provides-Extra: torch
Requires-Dist: torch <=2.2.2,>=1.3.0 ; extra == 'torch'
Requires-Dist: pydantic >=2.0 ; extra == 'torch'
Requires-Dist: pandas >=1.3.0 ; extra == 'torch'
Requires-Dist: humanize >=2.0.0 ; extra == 'torch'
Requires-Dist: tzlocal >=2.1 ; extra == 'torch'
Requires-Dist: requests >=2.0.0 ; extra == 'torch'
